pykrx_mcp/__about__.py
pykrx_mcp/__init__.py
pykrx_mcp/server.py
pykrx_mcp/prompts/__init__.py
pykrx_mcp/prompts/investor_flow.py
pykrx_mcp/prompts/screening.py
pykrx_mcp/prompts/stock_analysis.py
pykrx_mcp/prompts/stock_data.py
pykrx_mcp/resources/__init__.py
pykrx_mcp/resources/info.py
pykrx_mcp/resources/manual.py
pykrx_mcp/tools/__init__.py
pykrx_mcp/tools/etf_price.py
pykrx_mcp/tools/fundamental.py
pykrx_mcp/tools/market_cap.py
pykrx_mcp/tools/stock_price.py
pykrx_mcp/tools/ticker_info.py
pykrx_mcp/tools/trading_value.py
pykrx_mcp/utils/__init__.py
pykrx_mcp/utils/decorators.py
pykrx_mcp/utils/formatters.py
pykrx_mcp/utils/validators.py
pykrx_mcp-0.1.3.dist-info/METADATA
pykrx_mcp-0.1.3.dist-info/WHEEL
pykrx_mcp-0.1.3.dist-info/entry_points.txt
pykrx_mcp-0.1.3.dist-info/licenses/LICENSE
pykrx_mcp-0.1.3.dist-info/RECORD
