Metadata-Version: 2.4
Name: pykrx-mcp
Version: 0.1.3
Summary: MCP server for pykrx - Korean stock market data library
Project-URL: Homepage, https://github.com/sharebook-kr/pykrx-mcp
Project-URL: Repository, https://github.com/sharebook-kr/pykrx-mcp
Project-URL: Issues, https://github.com/sharebook-kr/pykrx-mcp/issues
Author-email: sharebook-kr <help@stockplus.com>
License: MIT
License-File: LICENSE
Keywords: ai-agent,kosdaq,kospi,krx,mcp,pykrx
Classifier: Development Status :: 4 - Beta
Classifier: Intended Audience :: Developers
Classifier: License :: OSI Approved :: MIT License
Classifier: Programming Language :: Python :: 3
Classifier: Programming Language :: Python :: 3.10
Classifier: Programming Language :: Python :: 3.11
Classifier: Programming Language :: Python :: 3.12
Requires-Python: >=3.10
Requires-Dist: mcp>=1.1.2
Requires-Dist: pandas>=2.0.0
Requires-Dist: pykrx>=1.0.46
Requires-Dist: setuptools>=65.0.0
